{
  "type": {
    "name": "compactmachines:compact_world",
    "ultrawarm": false,
    "natural": false,
    "piglin_safe": false,
    "respawn_anchor_works": false,
    "bed_works": false,
    "has_raids": false,
    "has_skylight": true,
    "has_ceiling": false,
    "coordinate_scale": 1,
    "ambient_light": 0,
    "logical_height": 256,
    "infiniburn": "minecraft:infiniburn_overworld"
  },
  "generator": {
    "type": "minecraft:flat",
    "settings": {
      "biome": "minecraft:plains",
      "layers": [
        {
          "block": "minecraft:air",
          "height": 1
        }
      ],
      "structures": {
        "stronghold": {
          "distance": 0,
          "count": 0,
          "spread": 0
        },

        "structures": {}
      }
    }
  }
}